hash/__init__.py
hash/dag.py
hash/errors.py
hash/logs.py
hash/utils.py
hash/cli/__init__.py
hash/cli/main.py
hash/core/__init__.py
hash/core/action.py
hash/core/execute.py
hash/core/hash.py
hash/core/main.py
hash/core/planner.py
hash/core/state.py
hash/core/templates.py
hash/resources/__init__.py
hash/resources/base.py
hash/resources/targets.py
hash/store/__init__.py
hash/store/base.py
hashcore-0.2.1.dist-info/LICENSE
hashcore-0.2.1.dist-info/METADATA
hashcore-0.2.1.dist-info/WHEEL
hashcore-0.2.1.dist-info/entry_points.txt
hashcore-0.2.1.dist-info/top_level.txt
hashcore-0.2.1.dist-info/RECORD
